odoo8_addon_account_invoice_constraint_chronology-8.0.1.0.1-py2.7-nspkg.pth
odoo8_addon_account_invoice_constraint_chronology-8.0.1.0.1.dist-info/top_level.txt
odoo8_addon_account_invoice_constraint_chronology-8.0.1.0.1.dist-info/WHEEL
odoo8_addon_account_invoice_constraint_chronology-8.0.1.0.1.dist-info/RECORD
odoo8_addon_account_invoice_constraint_chronology-8.0.1.0.1.dist-info/metadata.json
odoo8_addon_account_invoice_constraint_chronology-8.0.1.0.1.dist-info/DESCRIPTION.rst
odoo8_addon_account_invoice_constraint_chronology-8.0.1.0.1.dist-info/METADATA
odoo8_addon_account_invoice_constraint_chronology-8.0.1.0.1.dist-info/namespace_packages.txt
odoo_addons/account_invoice_constraint_chronology/post_install.py
odoo_addons/account_invoice_constraint_chronology/__openerp__.py
odoo_addons/account_invoice_constraint_chronology/__init__.py
odoo_addons/account_invoice_constraint_chronology/README.rst
odoo_addons/account_invoice_constraint_chronology/view/account_journal.xml
odoo_addons/account_invoice_constraint_chronology/i18n/ja.po
odoo_addons/account_invoice_constraint_chronology/i18n/zh_CN.po
odoo_addons/account_invoice_constraint_chronology/i18n/ru.po
odoo_addons/account_invoice_constraint_chronology/i18n/pt.po
odoo_addons/account_invoice_constraint_chronology/i18n/it.po
odoo_addons/account_invoice_constraint_chronology/i18n/es.po
odoo_addons/account_invoice_constraint_chronology/i18n/nl_BE.po
odoo_addons/account_invoice_constraint_chronology/i18n/ar.po
odoo_addons/account_invoice_constraint_chronology/i18n/lt.po
odoo_addons/account_invoice_constraint_chronology/i18n/ro.po
odoo_addons/account_invoice_constraint_chronology/i18n/tr.po
odoo_addons/account_invoice_constraint_chronology/i18n/mk.po
odoo_addons/account_invoice_constraint_chronology/i18n/hr.po
odoo_addons/account_invoice_constraint_chronology/i18n/es_EC.po
odoo_addons/account_invoice_constraint_chronology/i18n/zh_TW.po
odoo_addons/account_invoice_constraint_chronology/i18n/hu.po
odoo_addons/account_invoice_constraint_chronology/i18n/ca.po
odoo_addons/account_invoice_constraint_chronology/i18n/id.po
odoo_addons/account_invoice_constraint_chronology/i18n/es_CR.po
odoo_addons/account_invoice_constraint_chronology/i18n/sl.po
odoo_addons/account_invoice_constraint_chronology/i18n/sr@latin.po
odoo_addons/account_invoice_constraint_chronology/i18n/th.po
odoo_addons/account_invoice_constraint_chronology/i18n/cs.po
odoo_addons/account_invoice_constraint_chronology/i18n/pt_PT.po
odoo_addons/account_invoice_constraint_chronology/i18n/nb.po
